{
  "id": "f2364183db85418197ed323432b4ae43",
  "namespace": "ue",
  "title": "RPG Vampire Icons",
  "description": "RPG Vampire Icons - 100 icons for your game.",
  "longDescription": "<p>The set includes vampire items, voodoo icons, scrolls, package, monster parths, gem etc.</p>",
  "status": "ACTIVE",
  "productSlug": null,
  "urlSlug": "rpg-vampire-icons",
  "creationDate": "2024-09-12T12:43:57.157Z",
  "lastModifiedDate": "2024-09-27T13:43:09.216Z",
  "effectiveDate": "2024-09-12T12:43:57.100Z",
  "viewableDate": null,
  "developer": null,
  "seller": {
    "id": "o-wv7579e5u4h9lt3srvlvp8g2fm46yf",
    "name": "A-ravlik"
  },
  "linkedOfferId": null,
  "isFeatured": false,
  "ignoreOrder": false,
  "freeDays": 0,
  "collectionOfferIds": [],
  "technicalDetails": "<p>Features:</p><ul><li>The set includes 100 icons </li><li>There are transparent PNG</li><li>256×256 pixels size</li></ul><p><br /></p>",
  "recurrence": "ONCE",
  "categories": [
    {
      "path": "assets/2d"
    },
    {
      "path": "assets"
    }
  ],
  "tags": [
    {
      "id": null,
      "name": null,
      "namespace": null,
      "aliases": null,
      "operator": null,
      "created": null,
      "updated": null,
      "status": null,
      "referenceCount": null,
      "comment": null
    },
    {
      "id": null,
      "name": null,
      "namespace": null,
      "aliases": null,
      "operator": null,
      "created": null,
      "updated": null,
      "status": null,
      "referenceCount": null,
      "comment": null
    },
    {
      "id": "1203",
      "name": "Multiplayer",
      "namespace": "epic",
      "aliases": [],
      "operator": null,
      "created": "2019-06-20T11:59:59.171Z",
      "updated": "2024-03-28T21:49:29.573Z",
      "status": "ACTIVE",
      "referenceCount": 1846,
      "comment": null
    },
    {
      "id": null,
      "name": null,
      "namespace": null,
      "aliases": null,
      "operator": null,
      "created": null,
      "updated": null,
      "status": null,
      "referenceCount": null,
      "comment": null
    },
    {
      "id": null,
      "name": null,
      "namespace": null,
      "aliases": null,
      "operator": null,
      "created": null,
      "updated": null,
      "status": null,
      "referenceCount": null,
      "comment": null
    },
    {
      "id": null,
      "name": null,
      "namespace": null,
      "aliases": null,
      "operator": null,
      "created": null,
      "updated": null,
      "status": null,
      "referenceCount": null,
      "comment": null
    },
    {
      "id": null,
      "name": null,
      "namespace": null,
      "aliases": null,
      "operator": null,
      "created": null,
      "updated": null,
      "status": null,
      "referenceCount": null,
      "comment": null
    },
    {
      "id": null,
      "name": null,
      "namespace": null,
      "aliases": null,
      "operator": null,
      "created": null,
      "updated": null,
      "status": null,
      "referenceCount": null,
      "comment": null
    },
    {
      "id": null,
      "name": null,
      "namespace": null,
      "aliases": null,
      "operator": null,
      "created": null,
      "updated": null,
      "status": null,
      "referenceCount": null,
      "comment": null
    },
    {
      "id": null,
      "name": null,
      "namespace": null,
      "aliases": null,
      "operator": null,
      "created": null,
      "updated": null,
      "status": null,
      "referenceCount": null,
      "comment": null
    },
    {
      "id": null,
      "name": null,
      "namespace": null,
      "aliases": null,
      "operator": null,
      "created": null,
      "updated": null,
      "status": null,
      "referenceCount": null,
      "comment": null
    },
    {
      "id": null,
      "name": null,
      "namespace": null,
      "aliases": null,
      "operator": null,
      "created": null,
      "updated": null,
      "status": null,
      "referenceCount": null,
      "comment": null
    },
    {
      "id": "1247",
      "name": "Metroidvania",
      "namespace": "epic",
      "aliases": [],
      "operator": null,
      "created": "2019-06-20T12:00:21.277Z",
      "updated": "2023-07-31T20:24:00.951Z",
      "status": "ACTIVE",
      "referenceCount": 257,
      "comment": null
    }
  ],
  "customAttributes": [
    {
      "key": "FabListingId",
      "value": "da67d233-b45a-4b3a-b01e-e81218682c3f"
    }
  ],
  "keyImages": [
    {
      "type": "Screenshot",
      "url": "https://cdn1.epicgames.com/ue/product/Screenshot/CoverImagevam-1920x1080-2e2407cdde40d16b260afd4623a136fc.png",
      "md5": "2e2407cdde40d16b260afd4623a136fc",
      "size": 1092040,
      "uploadedDate": "2024-09-10T13:24:28.821Z",
      "width": 1920,
      "height": 1080
    },
    {
      "type": "Screenshot",
      "url": "https://cdn1.epicgames.com/ue/product/Screenshot/screen-1920x1080-b0b1be016de4b0804ba85beaf7147d9e.png",
      "md5": "b0b1be016de4b0804ba85beaf7147d9e",
      "size": 1707151,
      "uploadedDate": "2024-09-10T13:24:29.332Z",
      "width": 1920,
      "height": 1080
    },
    {
      "type": "Screenshot",
      "url": "https://cdn1.epicgames.com/ue/product/Screenshot/screen1-1920x1080-18581156afa16942030fa81ca1fb1fa2.png",
      "md5": "18581156afa16942030fa81ca1fb1fa2",
      "size": 1743028,
      "uploadedDate": "2024-09-10T13:24:29.879Z",
      "width": 1920,
      "height": 1080
    },
    {
      "type": "Thumbnail",
      "url": "https://cdn1.epicgames.com/ue/product/Thumbnail/RPGVampireIcons_thumb-284x284-8ea8c9defe43f0eecdb69761aad6567d.png",
      "md5": "8ea8c9defe43f0eecdb69761aad6567d",
      "size": 80751,
      "uploadedDate": "2024-09-10T13:24:30.359Z",
      "width": 284,
      "height": 284
    },
    {
      "type": "Featured",
      "url": "https://cdn1.epicgames.com/ue/product/Featured/RPGVampireIcons_featured-894x488-bba7aaee17b6a6d7afbd869ee691a50e.png",
      "md5": "bba7aaee17b6a6d7afbd869ee691a50e",
      "size": 419723,
      "uploadedDate": "2024-09-10T13:24:30.465Z",
      "width": 894,
      "height": 488
    },
    {
      "type": "Snapshot",
      "url": "https://cdn1.epicgames.com/ue/product/Snapshot/CoverImagevam-1920x1080-2e2407cdde40d16b260afd4623a136fc_Snapshot.png",
      "md5": "cd68f12826a14c824c97e7a4fd1c312e",
      "size": 8364,
      "uploadedDate": "2024-09-10T13:24:29.184Z",
      "width": 150,
      "height": 74
    },
    {
      "type": "Snapshot",
      "url": "https://cdn1.epicgames.com/ue/product/Snapshot/screen-1920x1080-b0b1be016de4b0804ba85beaf7147d9e_Snapshot.png",
      "md5": "70c8c94313ca7a59c96d3baa8a169a54",
      "size": 9435,
      "uploadedDate": "2024-09-10T13:24:29.669Z",
      "width": 150,
      "height": 74
    },
    {
      "type": "Snapshot",
      "url": "https://cdn1.epicgames.com/ue/product/Snapshot/screen1-1920x1080-18581156afa16942030fa81ca1fb1fa2_Snapshot.png",
      "md5": "4dc5aba4aeff994743ced941d116640e",
      "size": 9852,
      "uploadedDate": "2024-09-10T13:24:30.220Z",
      "width": 150,
      "height": 74
    }
  ],
  "items": [
    {
      "id": "6c787682bb45421d91b9e684ac3d8c08"
    }
  ],
  "catalogNs": null
}